sthelper/__init__.py
sthelper/_session.py
sthelper/gsheet/__init__.py
sthelper/gsheet/_gsheet.py
sthelper/widgets/__init__.py
sthelper/widgets/toc.py
StreamHelper-0.3.0.dist-info/LICENSE
StreamHelper-0.3.0.dist-info/METADATA
StreamHelper-0.3.0.dist-info/WHEEL
StreamHelper-0.3.0.dist-info/top_level.txt
StreamHelper-0.3.0.dist-info/RECORD
