Metadata-Version: 2.1
Name: StreamHelper
Version: 0.3.0
Summary: A package of RL algorithms
Home-page: https://github.com/leoxiang66/streamlit-apps/tree/toolkit
Author: Tao Xiang
Author-email: tao.xiang@tum.de
Classifier: Programming Language :: Python :: 3.10
Classifier: License :: OSI Approved :: MIT License
License-File: LICENSE
Requires-Dist: streamlit
Requires-Dist: shillelagh (==1.1.5)
Requires-Dist: shillelagh[gsheetsapi]
